[
	{
		"fgordr.fggods001":"GODS4BC992BAC99ACBC85F6F",
		"fgordr.fggods002":"200001478052661640",
		"fgordr.fggods003":"银项链-RFD",
		"fgordr.fgtrns016":"CALCED3A128C25324782840A6",
		"fgordr.fgtrns017":"CALCED3A128C25324782840A6",
		"show":"银项链-RFD",
		"column2":[
			{
				"billing":"ptww",
				"proName":"注塑B组",
				"id":"PLUS42F7BEA846D64030BEF7",
				"wagesDto":{
					"valuation":{
						"valuationNumber":1,
						"valuationValue":1
					},
					"valuations":[
						{
							"valuationNumber":1,
							"valuationValue":1
						}
					]
				},
				"wagesType":"ptdj",
				"column3":[
					{
						"email":"xavier.lin@szfurong.com",
						"nickname":"林值",
						"userId":"20000160810PLUS000027",
						"mobile":"13924604230"	
					},
					{
						"email":"xavier.lin@szfurong.com",
						"nickname":"test",
						"userId":"20000160810PLUS000027",
						"mobile":"13924604230"	
					}

				]
			},
			{
				"billing":"ptww",
				"proName":"注塑C组",
				"id":"PLUS42F7BEA846D64030BEF8",
				"wagesDto":{
					"valuation":{
						"valuationNumber":1,
						"valuationValue":1
					},
					"valuations":[
						{
							"valuationNumber":1,
							"valuationValue":1
						}
					]
				},
				"wagesType":"ptdj",
				"column3":[
					{
						"email":"xavier.lin@szfurong.com",
						"nickname":"林值",
						"userId":"20000160810PLUS000027",
						"mobile":"13924604230"	
					},
					{
						"email":"xavier.lin@szfurong.com",
						"nickname":"test",
						"userId":"20000160810PLUS000027",
						"mobile":"13924604230"	
					}

				]
			}
		]
	},
	{
		"fgordr.fggods001":"GODS4AB2AF10E7CC58C3DE19",
		"fgordr.fggods002":"200001478052661640",
		"fgordr.fggods003":"金",
		"fgordr.fgtrns016":"CALCED3A128C25324782840A6",
		"fgordr.fgtrns017":"CALCED3A128C25324782840A6",
		"show":"银项链-RFD",
		"column2":[
			{
				"billing":"ptww",
				"proName":"注塑B组",
				"id":"PLUS42F7BEA846D64030BEF7",
				"wagesDto":{
					"valuation":{
						"valuationNumber":1,
						"valuationValue":1
					},
					"valuations":[
						{
							"valuationNumber":1,
							"valuationValue":1
						}
					]
				},
				"wagesType":"ptdj",
				"column3":[
					{
						"email":"xavier.lin@szfurong.com",
						"nickname":"林值",
						"userId":"20000160810PLUS000027",
						"mobile":"13924604230"	
					},
					{
						"email":"xavier.lin@szfurong.com",
						"nickname":"test",
						"userId":"20000160810PLUS000027",
						"mobile":"13924604230"	
					}

				]
			},
			{
				"billing":"ptww",
				"proName":"注塑C组",
				"id":"PLUS42F7BEA846D64030BEF8",
				"wagesDto":{
					"valuation":{
						"valuationNumber":1,
						"valuationValue":1
					},
					"valuations":[
						{
							"valuationNumber":1,
							"valuationValue":1
						}
					]
				},
				"wagesType":"ptdj",
				"column3":[
					{
						"email":"xavier.lin@szfurong.com",
						"nickname":"林值",
						"userId":"20000160810PLUS000027",
						"mobile":"13924604230"	
					},
					{
						"email":"xavier.lin@szfurong.com",
						"nickname":"test",
						"userId":"20000160810PLUS000027",
						"mobile":"13924604230"	
					}

				]
			}
		]
	}
]